{
  "db_name": "PostgreSQL",
  "query": "WITH entities AS (SELECT created_at, id FROM bria_payouts WHERE (COALESCE((created_at, id) < ($3, $2), $2 IS NULL)) ORDER BY created_at DESC, id DESC LIMIT $1) SELECT i.id AS \"entity_id: PayoutId\", e.sequence, e.event, e.recorded_at FROM entities i JOIN bria_payout_events e ON i.id = e.id ORDER BY i.created_at desc, i.id desc, i.id, e.sequence",
  "describe": {
    "columns": [
      {
        "ordinal": 0,
        "name": "entity_id: PayoutId",
        "type_info": "Uuid"
      },
      {
        "ordinal": 1,
        "name": "sequence",
        "type_info": "Int4"
      },
      {
        "ordinal": 2,
        "name": "event",
        "type_info": "Jsonb"
      },
      {
        "ordinal": 3,
        "name": "recorded_at",
        "type_info": "Timestamptz"
      }
    ],
    "parameters": {
      "Left": [
        "Int8",
        "Uuid",
        "Timestamptz"
      ]
    },
    "nullable": [
      false,
      false,
      false,
      false
    ]
  },
  "hash": "a731798d488c3b533cad8296ef15f165f34f1668283990a5b89bae0362ddd7fe"
}
