{
  "db_name": "PostgreSQL",
  "query": "WITH entities AS (\n            SELECT *\n            FROM bria_addresses\n            WHERE account_id = $1 AND address = $2) SELECT i.id AS \"entity_id: Repo__Id\", e.sequence, e.event, CASE WHEN $3 THEN e.context ELSE NULL::jsonb END as \"context: es_entity::ContextData\", e.recorded_at FROM entities i JOIN bria_address_events e ON i.id = e.id ORDER BY i.id, e.sequence",
  "describe": {
    "columns": [
      {
        "ordinal": 0,
        "name": "entity_id: Repo__Id",
        "type_info": "Uuid"
      },
      {
        "ordinal": 1,
        "name": "sequence",
        "type_info": "Int4"
      },
      {
        "ordinal": 2,
        "name": "event",
        "type_info": "Jsonb"
      },
      {
        "ordinal": 3,
        "name": "context: es_entity::ContextData",
        "type_info": "Jsonb"
      },
      {
        "ordinal": 4,
        "name": "recorded_at",
        "type_info": "Timestamptz"
      }
    ],
    "parameters": {
      "Left": [
        "Uuid",
        "Text",
        "Bool"
      ]
    },
    "nullable": [
      false,
      false,
      false,
      null,
      false
    ]
  },
  "hash": "640cb941e8bc937e7c03ade967c55fb36c6e4a98a93b2b6d493b1ba70aa09ad2"
}
